equine_webapp/.gitignore
equine_webapp/__init__.py
equine_webapp/_version.py
equine_webapp/flask_server.py
equine_webapp/utils.py
equine_webapp/client/404.html
equine_webapp/client/EQUI(NE)^2_Full_Logo.svg
equine_webapp/client/EQUI(NE)^2_Logo.svg
equine_webapp/client/EQUI(NE)^2_Text.svg
equine_webapp/client/EQUINE2_fav.svg
equine_webapp/client/dashboard.html
equine_webapp/client/demo.html
equine_webapp/client/download.html
equine_webapp/client/favicon.ico
equine_webapp/client/favicon.svg
equine_webapp/client/index.html
equine_webapp/client/model-summary-page.html
equine_webapp/client/ood.png
equine_webapp/client/settings.html
equine_webapp/client/training.html
equine_webapp/client/ScatterUQ-demo-images/FashionMNIST-ID_MNIST-OOD/images/class-0_support-0.jpg
equine_webapp/client/ScatterUQ-demo-images/FashionMNIST-ID_MNIST-OOD/images/class-0_support-1.jpg
equine_webapp/client/ScatterUQ-demo-images/FashionMNIST-ID_MNIST-OOD/images/class-0_support-2.jpg
equine_webapp/client/ScatterUQ-demo-images/FashionMNIST-ID_MNIST-OOD/images/class-0_support-3.jpg
equine_webapp/client/ScatterUQ-demo-images/FashionMNIST-ID_MNIST-OOD/images/class-0_support-4.jpg
equine_webapp/client/ScatterUQ-demo-images/FashionMNIST-ID_MNIST-OOD/images/class-0_support-5.jpg
equine_webapp/client/ScatterUQ-demo-images/FashionMNIST-ID_MNIST-OOD/images/class-0_support-6.jpg
equine_webapp/client/ScatterUQ-demo-images/FashionMNIST-ID_MNIST-OOD/images/class-0_support-7.jpg
equine_webapp/client/ScatterUQ-demo-images/FashionMNIST-ID_MNIST-OOD/images/class-0_support-8.jpg
equine_webapp/client/ScatterUQ-demo-images/FashionMNIST-ID_MNIST-OOD/images/class-0_support-9.jpg
equine_webapp/client/ScatterUQ-demo-images/FashionMNIST-ID_MNIST-OOD/images/class-1_support-0.jpg
equine_webapp/client/ScatterUQ-demo-images/FashionMNIST-ID_MNIST-OOD/images/class-1_support-1.jpg
equine_webapp/client/ScatterUQ-demo-images/FashionMNIST-ID_MNIST-OOD/images/class-1_support-2.jpg
equine_webapp-0.1.dev94.dist-info/LICENSE.txt
equine_webapp-0.1.dev94.dist-info/METADATA
equine_webapp-0.1.dev94.dist-info/WHEEL
equine_webapp-0.1.dev94.dist-info/entry_points.txt
equine_webapp-0.1.dev94.dist-info/top_level.txt
equine_webapp-0.1.dev94.dist-info/RECORD
