Metadata-Version: 2.2
Name: equine-webapp
Version: 0.1.dev94
Summary: Companion web application for EQUINE^2: Establishing Quantified Uncertainty for Neural Networks
Author: Allan Wollaber, Steven Jorgensen, Harry Li
Maintainer: Allan Wollaber, Steven Jorgensen, Harry Li
License: MIT
Project-URL: Homepage, https://mit-ll-responsible-ai.github.io/equine-webapp/
Project-URL: Bug Tracker, https://github.com/mit-ll-responsible-ai/equine-webapp/issues
Project-URL: Source, https://github.com/mit-ll-responsible-ai/equine-webapp
Keywords: machine learning,robustness,pytorch,responsible,AI
Classifier: Development Status :: 4 - Beta
Classifier: License :: OSI Approved :: MIT License
Classifier: Operating System :: OS Independent
Classifier: Intended Audience :: Science/Research
Classifier: Topic :: Scientific/Engineering
Classifier: Programming Language :: Python :: 3 :: Only
Requires-Python: >=3.9
License-File: LICENSE.txt
Requires-Dist: ariadne
Requires-Dist: equine>=0.1.5
Requires-Dist: flask
Requires-Dist: flask-cors
Requires-Dist: numpy
Requires-Dist: scikit-learn
Requires-Dist: torch
Requires-Dist: torchvision
Requires-Dist: umap-learn
Requires-Dist: waitress
Requires-Dist: zadu==0.1.1
Provides-Extra: tests
Requires-Dist: pytest>=3.8; extra == "tests"
Requires-Dist: hypothesis<6.113.0,>=6.105.0; extra == "tests"
Requires-Dist: pre-commit>=2.19; extra == "tests"
Requires-Dist: codespell; extra == "tests"
Provides-Extra: docs
Requires-Dist: mkdocs>=1.3; extra == "docs"
Requires-Dist: mkdocs-material; extra == "docs"
Requires-Dist: mkdocstrings-python; extra == "docs"
Requires-Dist: mkdocs-jupyter; extra == "docs"
Requires-Dist: mkdocs-literate-nav; extra == "docs"
Requires-Dist: mkdocs-gen-files; extra == "docs"
Requires-Dist: mkdocs-section-index; extra == "docs"
